{
  "notes": [
    {
      "id": "4441",
      "highlightColor": "#F3CCF3",
      "category": "lifestyle",
      "title": "ea molestias quasi exercitationem repellat qui ipsa sit aut",
      "description": "et iusto sed quo iure\nvoluptatem occaecati omnis eligendi aut ad\nvoluptatem doloribus vel accusantium quis pariatur\nmolestiae porro eius odio et labore et velit aut"
    },
    {
      "id": "5",
      "highlightColor": "#F3CCF3",
      "category": "personal",
      "title": "nesciunt quas odio",
      "description": "repudiandae veniam quaerat sunt sed\nalias aut fugiat sit autem sed est\nvoluptatem omnis possimus esse voluptatibus quis\nest aut tenetur dolor neque"
    },
    {
      "id": "6",
      "highlightColor": "#FFBE98",
      "category": "work",
      "title": "dolorem eum magni eos aperiam quia",
      "description": "ut aspernatur corporis harum nihil quis provident sequi\nmollitia nobis aliquid molestiae\nperspiciatis et ea nemo ab reprehenderit accusantium quas\nvoluptate dolores velit et doloremque molestiae"
    },
    {
      "id": "7",
      "highlightColor": "#ED7D31",
      "category": "personal",
      "title": "magnam facilis autem",
      "description": "dolore placeat quibusdam ea quo vitae\nmagni quis enim qui quis quo nemo aut saepe\nquidem repellat excepturi ut quia\nsunt ut sequi eos ea sed quas"
    },
    {
      "id": "8",
      "highlightColor": "#F3CCF3",
      "category": "lifestyle",
      "title": "dolorem dolore est ipsam",
      "description": "dignissimos aperiam dolorem qui eum\nfacilis quibusdam animi sint suscipit qui sint possimus cum\nquaerat magni maiores excepturi\nipsam ut commodi dolor voluptatum modi aut vitae"
    },
    {
      "id": "bad3cbb3-5223-4029-98d3-3c74013a2d5d",
      "title": "Buy groceries",
      "description": "Apple, orange, grapes, chips, chicken etc..",
      "highlightColor": "#F3CCF3",
      "category": "Personal"
    },
    {
      "id": "46353030-c224-4db9-94c9-8af7199e8ef3",
      "title": "Learn next js",
      "description": "Router, SSR, SSG etc..",
      "highlightColor": "#ED7D31",
      "category": "Work"
    },
    {
      "id": "de5bb110-de81-4994-bfa8-b5185f7aa5b9",
      "title": "Thinking of a note",
      "description": "testing testing",
      "highlightColor": "#FFBE98",
      "category": "Entertainment"
    },
    {
      "id": "0756f297-771a-49f6-a333-75ad8ee37082",
      "title": "Basic note",
      "description": "lorem ipsum asldkfjasldfkjla asdflkj asdlfkjsdlfj",
      "highlightColor": "#FFBE98",
      "category": "Entertainment"
    },
    {
      "id": "386d08af-c32c-4084-87a5-ac2fd8d85b40",
      "title": "Mani's note",
      "description": "Note body text asdlkj asdflkj 123l asdlfkj ",
      "highlightColor": "#FFBE98",
      "category": "Work"
    },
    {
      "id": "9d287fc8-7ba0-41fa-8f29-405b022e0732",
      "title": "Copilot note",
      "description": "# Dummy Note  ## To-Do List - Buy groceries - Walk the dog - Pay bills  ## Random Thoughts - Why do we park in driveways and drive on parkways? - If a tree falls in a forest and no one is around to hear it, does it make a sound?  Remember, this is just a playful note. Feel free to add your own content or customize it as needed! 😊",
      "highlightColor": "#ED7D31",
      "category": "Personal"
    }
  ]
}